Fluent_Test-3.0.0.dist-info/top_level.txt
Fluent_Test-3.0.0.dist-info/metadata.json
Fluent_Test-3.0.0.dist-info/RECORD
Fluent_Test-3.0.0.dist-info/WHEEL
Fluent_Test-3.0.0.dist-info/METADATA
Fluent_Test-3.0.0.dist-info/DESCRIPTION.rst
fluenttest/__init__.py
fluenttest/test_case.py
