Metadata-Version: 2.0
Name: Fluent-Test
Version: 3.0.0
Summary: Fluent testing for Python
Home-page: http://github.com/dave-shawley/fluent-test/
Author: Dave Shawley
Author-email: daveshawley@gmail.com
License: BSD
Platform: any
Classifier: Intended Audience :: Developers
Classifier: License :: OSI Approved :: BSD License
Classifier: Operating System :: OS Independent
Classifier: Programming Language :: Python
Requires-Dist: mock
